invenio_records_files/__init__.py
invenio_records_files/api.py
invenio_records_files/config.py
invenio_records_files/ext.py
invenio_records_files/links.py
invenio_records_files/models.py
invenio_records_files/serializer.py
invenio_records_files/utils.py
invenio_records_files/views.py
invenio_records_files/alembic/1ba76da94103_create_records_files_tables.py
invenio_records_files/alembic/2da9a03b0833_create_records_files_branch.py
invenio_records_files/alembic/4a5d5b4d4c2f_create_bucket_id_index.py
invenio_records_files/jsonschemas/__init__.py
invenio_records_files/jsonschemas/records-files/records-files-v1.0.0.json
invenio_records_files-2.0.0.dist-info/licenses/AUTHORS.rst
invenio_records_files-2.0.0.dist-info/licenses/LICENSE
invenio_records_files-2.0.0.dist-info/METADATA
invenio_records_files-2.0.0.dist-info/WHEEL
invenio_records_files-2.0.0.dist-info/entry_points.txt
invenio_records_files-2.0.0.dist-info/top_level.txt
invenio_records_files-2.0.0.dist-info/RECORD
