Metadata-Version: 2.4
Name: invenio-records-files
Version: 2.0.0
Summary: "Invenio modules that integrates records and files."
Home-page: https://github.com/inveniosoftware/invenio-records-files
Author: CERN
Author-email: info@inveniosoftware.org
License: MIT
Keywords: invenio records files
Platform: any
Classifier: Development Status :: 5 - Production/Stable
Requires-Python: >=3.7
License-File: LICENSE
License-File: AUTHORS.rst
Requires-Dist: invenio-base<3.0.0,>=1.2.2
Requires-Dist: invenio-files-rest<5.0.0,>=4.0.0
Requires-Dist: invenio-records<5.0.0,>=4.0.0
Requires-Dist: invenio-records-rest<5.0.0,>=4.0.0
Provides-Extra: tests
Requires-Dist: pytest-black>=0.6.0; extra == "tests"
Requires-Dist: invenio-indexer<5.0.0,>=4.0.0; extra == "tests"
Requires-Dist: mock>=1.3.0; extra == "tests"
Requires-Dist: pytest-invenio<5.0.0,>=4.0.0; extra == "tests"
Requires-Dist: Sphinx>=3; extra == "tests"
Provides-Extra: postgresql
Requires-Dist: invenio-db[postgresql,versioning]<3.0.0,>=2.2.0; extra == "postgresql"
Provides-Extra: mysql
Requires-Dist: invenio-db[mysql,versioning]<3.0.0,>=2.2.0; extra == "mysql"
Provides-Extra: sqlite
Requires-Dist: invenio-db[versioning]<3.0.0,>=2.2.0; extra == "sqlite"
Provides-Extra: elasticsearch7
Requires-Dist: invenio-search[elasticsearch7]<4.0.0,>=3.0.0; extra == "elasticsearch7"
Provides-Extra: opensearch2
Requires-Dist: invenio-search[opensearch2]<4.0.0,>=3.0.0; extra == "opensearch2"
Provides-Extra: docs
Requires-Dist: Sphinx>=3; extra == "docs"
Dynamic: license-file
